landelayo/__init__.py
landelayo/admin.py
landelayo/apps.py
landelayo/enum.py
landelayo/forms.py
landelayo/models.py
landelayo/occurrences.py
landelayo/serializers.py
landelayo/settings.py
landelayo/urls.py
landelayo/utils.py
landelayo/views.py
landelayo/migrations/0001_initial.py
landelayo/migrations/__init__.py
django_landelayo-1.0.1.dist-info/LICENSE
django_landelayo-1.0.1.dist-info/METADATA
django_landelayo-1.0.1.dist-info/WHEEL
django_landelayo-1.0.1.dist-info/top_level.txt
django_landelayo-1.0.1.dist-info/RECORD
