Metadata-Version: 2.1
Name: django-landelayo
Version: 1.0.1
Summary: 'A set of django rest apis to manage your calendar'
Home-page: https://github.com/StandaloneDynamics/django-landelayo
Author: Menzi Mthembu
License: GPL v3.0
Classifier: Environment :: Web Environment
Classifier: Framework :: Django
Classifier: Framework :: Django :: 4.2
Classifier: Intended Audience :: Developers
Classifier: License :: OSI Approved :: GNU General Public License v3 (GPLv3)
Classifier: Operating System :: OS Independent
Classifier: Programming Language :: Python
Classifier: Programming Language :: Python :: 3
Classifier: Programming Language :: Python :: 3 :: Only
Classifier: Programming Language :: Python :: 3.8
Classifier: Programming Language :: Python :: 3.9
Classifier: Programming Language :: Python :: 3.10
Classifier: Programming Language :: Python :: 3.11
Classifier: Topic :: Internet :: WWW/HTTP
Classifier: Topic :: Internet :: WWW/HTTP :: Dynamic Content
Requires-Python: >=3.8
License-File: LICENSE
Requires-Dist: django ~=4.2
Requires-Dist: djangorestframework >=3.14
Requires-Dist: django-enumfield >=3.1
